{"cameraMode":{"drawMode":0,"name":"Shaded","section":"Shading Mode"},"sceneLighting":true,"audioPlay":false,"sceneViewState":{"m_AlwaysRefresh":false,"showFog":true,"showSkybox":true,"showFlares":true,"showImageEffects":true,"showParticleSystems":true,"showVisualEffectGraphs":true,"m_FxEnabled":true},"in2DMode":false,"pivot":{"x":-50.25400161743164,"y":17.73409652709961,"z":13.084714889526368},"rotation":{"x":-0.07501216232776642,"y":-0.9120330214500427,"z":0.19169332087039948,"w":-0.3549804389476776},"size":1.849906325340271,"orthographic":false}